eues/__init__.py
eues/eues.py
eues-0.1.2.dist-info/WHEEL
eues-0.1.2.dist-info/METADATA
eues-0.1.2.dist-info/RECORD
