Metadata-Version: 2.1
Name: eues
Version: 0.1.2
Summary: Einnahmeüberschussrechnung
Author: Marco Heins
Author-email: ruttercrash@posteo.de
Requires-Python: >=3.10,<4.0
Classifier: Programming Language :: Python :: 3
Classifier: Programming Language :: Python :: 3.10
